terminal_gemini/__init__.py
terminal_gemini/cli.py
terminal_gemini/main.py
terminal_gemini_cli-0.1.2.dist-info/METADATA
terminal_gemini_cli-0.1.2.dist-info/WHEEL
terminal_gemini_cli-0.1.2.dist-info/entry_points.txt
terminal_gemini_cli-0.1.2.dist-info/top_level.txt
terminal_gemini_cli-0.1.2.dist-info/RECORD
