Metadata-Version: 2.4
Name: terminal-gemini-cli
Version: 0.1.2
Summary: A simple CLI for chatting with Google Gemini from your terminal
Author-email: Mandar Wagh <mandarwagh90@gmail.com>
License: MIT
Requires-Python: >=3.8
Requires-Dist: requests
